PILTools/ImageTools.py
PILTools/__init__.py
PILTools/base.py
PILTools/core.py
PILTools/error.py
PIL_Tools-1.1.0.dist-info/LICENSE
PIL_Tools-1.1.0.dist-info/METADATA
PIL_Tools-1.1.0.dist-info/WHEEL
PIL_Tools-1.1.0.dist-info/top_level.txt
PIL_Tools-1.1.0.dist-info/RECORD
