Metadata-Version: 2.1
Name: PIL-Tools
Version: 1.1.0
Summary: An extension module for Pillow to add functions that help simplify some processes.
Home-page: https://pypi.python.org/pypi/PILTools
Author: Steven Shrewsbury
Author-email: 
License: MIT
Project-URL: Source, https://github.com/stshrewsburyDev/PIL-Tools
Project-URL: Documentation, https://pil-tools.readthedocs.io/en/latest/
Platform: UNKNOWN
Classifier: Programming Language :: Python
Classifier: Programming Language :: Python :: 3
Classifier: License :: OSI Approved :: MIT License
Classifier: Operating System :: OS Independent
Classifier: Topic :: Utilities
Classifier: Intended Audience :: Developers
Requires-Python: >=3.6
